{
  "parent": "minecraft:recipes/root",
  "rewards": {
    "recipes": [
      "croptopia:nougat"
    ]
  },
  "criteria": {
    "has_nuts": {
      "trigger": "minecraft:inventory_changed",
      "conditions": {
        "items": [
          {
            "tag": "${dependent}:nuts"
          }
        ]
      }
    },
    "has_the_recipe": {
      "trigger": "minecraft:recipe_unlocked",
      "conditions": {
        "recipe": "croptopia:nougat"
      }
    }
  },
  "requirements": [
    [
      "has_nuts",
      "has_the_recipe"
    ]
  ]
}