{
  "parent": "minecraft:recipes/root",
  "rewards": {
    "recipes": [
      "croptopia:shaped_bacon"
    ]
  },
  "criteria": {
    "has_knife": {
      "trigger": "minecraft:inventory_changed",
      "conditions": {
        "items": [
          {
            "items": ["croptopia:knife"]
          }
        ]
      }
    },
    "has_porkchop": {
      "trigger": "minecraft:inventory_changed",
      "conditions": {
        "items": [
          {
            "items": ["minecraft:porkchop"]
          }
        ]
      }
    },
    "has_the_recipe": {
      "trigger": "minecraft:recipe_unlocked",
      "conditions": {
        "recipe": "croptopia:shaped_bacon"
      }
    }
  },
  "requirements": [
    [
      "has_knife",
      "has_porkchop",
      "has_the_recipe"
    ]
  ]
}