{
  "parent": "minecraft:recipes/root",
  "rewards": {
    "recipes": [
      "croptopia:mango_sapling"
    ]
  },
  "criteria": {
    "has_mango": {
      "trigger": "minecraft:inventory_changed",
      "conditions": {
        "items": [
          {
            "items": [
              "croptopia:mango"
            ]
          }
        ]
      }
    },
    "has_the_recipe": {
      "trigger": "minecraft:recipe_unlocked",
      "conditions": {
        "recipe": "croptopia:mango_sapling"
      }
    }
  },
  "requirements": [
    [
      "has_mango",
      "has_the_recipe"
    ]
  ]
}