{
  "parent": "minecraft:recipes/root",
  "rewards": {
    "recipes": [
      "croptopia:mustard_to_mustard_seed_shapeless"
    ]
  },
  "criteria": {
    "has_mustard": {
      "trigger": "minecraft:inventory_changed",
      "conditions": {
        "items": [
          {
            "tag": "${dependent}:vegetables/mustard"
          }
        ]
      }
    },
    "has_the_recipe": {
      "trigger": "minecraft:recipe_unlocked",
      "conditions": {
        "recipe": "croptopia:mustard_to_mustard_seed_shapeless"
      }
    }
  },
  "requirements": [
    [
      "has_mustard",
      "has_the_recipe"
    ]
  ]
}